adlibo/__init__.py
adlibo/py.typed
adlibo-1.2.0.dist-info/METADATA
adlibo-1.2.0.dist-info/WHEEL
adlibo-1.2.0.dist-info/licenses/LICENSE
adlibo-1.2.0.dist-info/RECORD
