Metadata-Version: 2.4
Name: adlibo
Version: 1.2.0
Summary: Official Adlibo SDK for Python - AI Prompt Injection Protection
Project-URL: Homepage, https://www.adlibo.com
Project-URL: Documentation, https://www.adlibo.com/docs
Project-URL: Repository, https://github.com/adlibo/sdk-python
Project-URL: Issues, https://github.com/adlibo/sdk-python/issues
Author-email: Adlibo <info@adlibo.com>
License-Expression: MIT
License-File: LICENSE
Keywords: adlibo,ai,detection,jailbreak,llm,prompt-injection,protection,security
Classifier: Development Status :: 5 - Production/Stable
Classifier: Intended Audience :: Developers
Classifier: License :: OSI Approved :: MIT License
Classifier: Operating System :: OS Independent
Classifier: Programming Language :: Python :: 3
Classifier: Programming Language :: Python :: 3.8
Classifier: Programming Language :: Python :: 3.9
Classifier: Programming Language :: Python :: 3.10
Classifier: Programming Language :: Python :: 3.11
Classifier: Programming Language :: Python :: 3.12
Classifier: Topic :: Security
Classifier: Topic :: Software Development :: Libraries :: Python Modules
Requires-Python: >=3.8
Requires-Dist: httpx>=0.24.0
Provides-Extra: async
Requires-Dist: httpx[http2]>=0.24.0; extra == 'async'
Provides-Extra: dev
Requires-Dist: pytest-asyncio>=0.21.0; extra == 'dev'
Requires-Dist: pytest-httpx>=0.22.0; extra == 'dev'
Requires-Dist: pytest>=7.0.0; extra == 'dev'
